django_postgres_stats-1.0.0.dist-info/DESCRIPTION.rst
django_postgres_stats-1.0.0.dist-info/METADATA
django_postgres_stats-1.0.0.dist-info/metadata.json
django_postgres_stats-1.0.0.dist-info/pbr.json
django_postgres_stats-1.0.0.dist-info/RECORD
django_postgres_stats-1.0.0.dist-info/top_level.txt
django_postgres_stats-1.0.0.dist-info/WHEEL
postgres_stats/__init__.py
postgres_stats/aggregates.py
postgres_stats/functions.py
